{
  "fitnessActivity": "walking",
  "startTime": "2024-06-11T12:09:13.288Z",
  "endTime": "2024-06-11T12:33:01.869Z",
  "duration": "1426.739s",
  "segment": [{
    "fitnessActivity": "walking",
    "startTime": "2024-06-11T12:09:13.288Z",
    "endTime": "2024-06-11T12:33:00.027Z"
  }],
  "aggregate": [{
    "metricName": "com.google.heart_minutes.summary",
    "floatValue": 4.0
  }, {
    "metricName": "com.google.calories.expended",
    "floatValue": 95.30222696004725
  }, {
    "metricName": "com.google.step_count.delta",
    "intValue": 1669
  }, {
    "metricName": "com.google.distance.delta",
    "floatValue": 1069.0542885678233
  }, {
    "metricName": "com.google.speed.summary",
    "floatValue": 0.8818536146899019
  }, {
    "metricName": "com.google.active_minutes",
    "intValue": 22
  }]
}